mlrun_pipelines/common/__init__.py
mlrun_pipelines/common/client.py
mlrun_pipelines/common/constants.py
mlrun_pipelines/common/helpers.py
mlrun_pipelines/common/imports.py
mlrun_pipelines/common/models.py
mlrun_pipelines/common/mounts.py
mlrun_pipelines/common/ops.py
mlrun_pipelines_kfp_common-0.5.9.dist-info/METADATA
mlrun_pipelines_kfp_common-0.5.9.dist-info/WHEEL
mlrun_pipelines_kfp_common-0.5.9.dist-info/top_level.txt
mlrun_pipelines_kfp_common-0.5.9.dist-info/RECORD
